admin_extra_buttons/__init__.py
admin_extra_buttons/api.py
admin_extra_buttons/apps.py
admin_extra_buttons/buttons.py
admin_extra_buttons/decorators.py
admin_extra_buttons/handlers.py
admin_extra_buttons/mixins.py
admin_extra_buttons/py.typed
admin_extra_buttons/types.pyi
admin_extra_buttons/utils.py
admin_extra_buttons/version.py
admin_extra_buttons/static/admin_extra_buttons.css
admin_extra_buttons/static/admin_extra_buttons.css.map
admin_extra_buttons/static/admin_extra_buttons.js
admin_extra_buttons/static/admin_extra_buttons.min.js
admin_extra_buttons/static/admin_extra_buttons.scss
admin_extra_buttons/templates/admin_extra_buttons/action_page.html
admin_extra_buttons/templates/admin_extra_buttons/change_form.html
admin_extra_buttons/templates/admin_extra_buttons/change_list.html
admin_extra_buttons/templates/admin_extra_buttons/confirm.html
admin_extra_buttons/templates/admin_extra_buttons/includes/action_buttons.html
admin_extra_buttons/templates/admin_extra_buttons/includes/attrs.html
admin_extra_buttons/templates/admin_extra_buttons/includes/button.html
admin_extra_buttons/templates/admin_extra_buttons/includes/change_form_buttons.html
admin_extra_buttons/templates/admin_extra_buttons/includes/change_list_buttons.html
admin_extra_buttons/templates/admin_extra_buttons/includes/choice.html
admin_extra_buttons/templatetags/__init__.py
admin_extra_buttons/templatetags/extra_buttons.py
django_admin_extra_buttons-2.1.2.dist-info/METADATA
django_admin_extra_buttons-2.1.2.dist-info/WHEEL
django_admin_extra_buttons-2.1.2.dist-info/licenses/LICENSE
django_admin_extra_buttons-2.1.2.dist-info/RECORD
